CHANGELOG
LICENSE
MANIFEST.in
NOTICE
README.md
setup.py
test.py
lz4/LICENSE
lz4/NEWS
lz4/lz4.c
lz4/lz4.h
lz4/lz4frame.c
lz4/lz4frame.h
lz4/lz4frame_static.h
lz4/lz4hc.c
lz4/lz4hc.h
lz4/xxhash.c
lz4/xxhash.h
lz4framed/__init__.py
lz4framed/__main__.py
lz4framed/compat.py
lz4framed/py-lz4framed.c
py/lib/python3.6/site-packages/Pygments-2.5.2.dist-info/LICENSE
py/lib/python3.6/site-packages/SecretStorage-3.1.1.dist-info/LICENSE
py/lib/python3.6/site-packages/cryptography-2.8.dist-info/LICENSE
py/lib/python3.6/site-packages/entrypoints-0.3.dist-info/LICENSE
py/lib/python3.6/site-packages/importlib_metadata-0.23.dist-info/LICENSE
py/lib/python3.6/site-packages/jeepney-0.4.1.dist-info/tmp/tmp4trcl86h/jeepney-0.4.1/LICENSE
py/lib/python3.6/site-packages/keyring-19.2.0.dist-info/LICENSE
py/lib/python3.6/site-packages/more_itertools-8.0.0.dist-info/LICENSE
py/lib/python3.6/site-packages/readme_renderer-24.0.dist-info/LICENSE
py/lib/python3.6/site-packages/requests-2.22.0.dist-info/LICENSE
py/lib/python3.6/site-packages/requests_toolbelt-0.9.1.dist-info/LICENSE
py/lib/python3.6/site-packages/setuptools-42.0.1.dist-info/LICENSE
py/lib/python3.6/site-packages/six-1.13.0.dist-info/LICENSE
py/lib/python3.6/site-packages/twine-3.1.1.dist-info/LICENSE
py/lib/python3.6/site-packages/zipp-0.6.0.dist-info/LICENSE
py/lib64/python3.6/site-packages/Pygments-2.5.2.dist-info/LICENSE
py/lib64/python3.6/site-packages/SecretStorage-3.1.1.dist-info/LICENSE
py/lib64/python3.6/site-packages/cryptography-2.8.dist-info/LICENSE
py/lib64/python3.6/site-packages/entrypoints-0.3.dist-info/LICENSE
py/lib64/python3.6/site-packages/importlib_metadata-0.23.dist-info/LICENSE
py/lib64/python3.6/site-packages/jeepney-0.4.1.dist-info/tmp/tmp4trcl86h/jeepney-0.4.1/LICENSE
py/lib64/python3.6/site-packages/keyring-19.2.0.dist-info/LICENSE
py/lib64/python3.6/site-packages/more_itertools-8.0.0.dist-info/LICENSE
py/lib64/python3.6/site-packages/readme_renderer-24.0.dist-info/LICENSE
py/lib64/python3.6/site-packages/requests-2.22.0.dist-info/LICENSE
py/lib64/python3.6/site-packages/requests_toolbelt-0.9.1.dist-info/LICENSE
py/lib64/python3.6/site-packages/setuptools-42.0.1.dist-info/LICENSE
py/lib64/python3.6/site-packages/six-1.13.0.dist-info/LICENSE
py/lib64/python3.6/site-packages/twine-3.1.1.dist-info/LICENSE
py/lib64/python3.6/site-packages/zipp-0.6.0.dist-info/LICENSE
py2/lib/python2.7/site-packages/setuptools-42.0.1.dist-info/LICENSE
py2/local/lib/python2.7/site-packages/setuptools-42.0.1.dist-info/LICENSE
py_lz4framed.egg-info/PKG-INFO
py_lz4framed.egg-info/SOURCES.txt
py_lz4framed.egg-info/dependency_links.txt
py_lz4framed.egg-info/not-zip-safe
py_lz4framed.egg-info/top_level.txt