Metadata-Version: 2.1
Name: py-lz4framed
Version: 0.14.0
Summary: LZ4Frame library for Python (via C bindings)
Home-page: https://github.com/Iotic-Labs/py-lz4framed
Author: Iotic Labs Ltd
Author-email: info@iotic-labs.com
Maintainer: Iotic Labs Ltd
Maintainer-email: vilnis.termanis@iotic-labs.com
License: Apache License 2.0
Keywords: lz4framed,lz4frame,lz4
Platform: UNKNOWN
Classifier: Development Status :: 5 - Production/Stable
Classifier: License :: OSI Approved :: Apache Software License
Classifier: Intended Audience :: Developers
Classifier: Programming Language :: C
Classifier: Programming Language :: Python
Classifier: Programming Language :: Python :: 2.7
Classifier: Programming Language :: Python :: 3.2
Classifier: Programming Language :: Python :: 3.3
Classifier: Programming Language :: Python :: 3.4
Classifier: Programming Language :: Python :: 3.5
Classifier: Programming Language :: Python :: 3.6
Classifier: Programming Language :: Python :: 3.7
Classifier: Topic :: Software Development :: Libraries
Classifier: Topic :: Software Development :: Libraries :: Python Modules
